stage_click-0.1.0a7.dist-info/licenses/LICENSE
stageclick/__init__.py
stageclick/log.py
stageclick/core/__init__.py
stageclick/core/image_processing.py
stageclick/core/input_controllers.py
stageclick/core/window_tools.py
stageclick/step_runner/__init__.py
stageclick/step_runner/commands.py
stageclick/step_runner/core.py
stageclick/step_runner/net.py
stageclick/step_runner/parsing.py
stageclick/step_runner/procedure_loader.py
stageclick/step_runner/runner.py
stageclick/step_runner/saving.py
stage_click-0.1.0a7.dist-info/METADATA
stage_click-0.1.0a7.dist-info/WHEEL
stage_click-0.1.0a7.dist-info/top_level.txt
stage_click-0.1.0a7.dist-info/RECORD
