Metadata-Version: 2.4
Name: stage-click
Version: 0.1.0a7
Summary: A template-focused mouse/keyboard controller window automation library for Windows.
Author-email: TheRealRazbi <therealrazbi@users.noreply.github.com>
License: Mozilla Public License Version 2.0
Project-URL: Homepage, https://github.com/TheRealRazbi/stageclick
Project-URL: Bug Tracker, https://github.com/TheRealRazbi/stageclick/issues
Keywords: automation,windows,template matching,screen control,pynput,pygetwindow,timing
Classifier: Programming Language :: Python :: 3
Classifier: Programming Language :: Python :: 3.11
Classifier: Operating System :: Microsoft :: Windows
Classifier: License :: OSI Approved :: Mozilla Public License 2.0 (MPL 2.0)
Requires-Python: >=3.11
License-File: LICENSE
Requires-Dist: pygetwindow<1.0,>=0.0.9
Requires-Dist: pynput<2.0,>=1.7.6
Requires-Dist: pywin32<400,>=306
Requires-Dist: pyperclip<2.0,>=1.8.2
Requires-Dist: opencv-python<5.0,>=4.9
Requires-Dist: pillow<11.0,>=10.3.0
Requires-Dist: screeninfo<1.0,>=0.8.1
Requires-Dist: psutil<6.0,>=5.9.8
Requires-Dist: numpy<2.0,>=1.26.4
Requires-Dist: mss<10.0,>=9.0.1
Requires-Dist: termcolor<4.0,>=3.1.0
Requires-Dist: rich<15.0,>=14.0.0
Dynamic: license-file
